LICENSE
py_events/__init__.py
py_events/event.py
py_events/misc.py
py_events-0.1.2.dist-info/LICENSE
py_events-0.1.2.dist-info/WHEEL
py_events-0.1.2.dist-info/METADATA
py_events-0.1.2.dist-info/RECORD
