Metadata-Version: 2.1
Name: py-events
Version: 0.1.2
Summary: Basic event system for python
Home-page: https://github.com/Jordan-Cottle/Events
License: MIT
Keywords: event
Author: Jordan Cottle
Author-email: jordancottle622@gmail.com
Requires-Python: >=3.6.2,<4.0.0
Classifier: License :: OSI Approved :: MIT License
Classifier: Programming Language :: Python :: 3
Classifier: Programming Language :: Python :: 3.7
Classifier: Programming Language :: Python :: 3.8
Classifier: Programming Language :: Python :: 3.9
Project-URL: Repository, https://github.com/Jordan-Cottle/Events
